{
    "apropos" : [
        {
            "id" : "aPropos",
            "titre" : "Mickaël, 34 ans",
            "metier" : "Développeur web FullStack",
            "lieu" : "Loire, FRANCE"
        },
        {
            "id" : "softSkills",
            "titre" : "Soft skills",
            "items" : [
                {"libelle" : "Rigueur"},
                {"libelle" : "Autonomie"},
                {"libelle" : "Esprit d'équipe"},
                {"libelle" : "Pédagogie"}
            ]
        },
        {
            "id" : "description",
            "texte" : "Je participe aux projets digitaux en intervenant dans la gestion de projet, l’expertise fonctionnelle et l’expérience utilisateur. Optimisme, bonne humeur, organisation et esprit d’équipe sont les maîtres mots pour mener à bien mes missions."
        },
        {
            "id" : "formation",
            "titre" : "Formation",
            "etablissements" : [
                {
                    "libelle" : "Webecom",
                    "diplomes" : [
                        {"libelle" : "Certification RNCP Développeur web"}
                    ]
                },
                {
                    "libelle" : "CNAM Saint-Etienne",
                    "diplomes" : [
                        {"libelle" : "Ingénieur spécialité informatique"},
                        {"libelle" : "RNCP Concepteur-Architecte"},
                        {"libelle" : "Licence générale d'informatique"}
                    ]
                },
                {
                    "libelle" : "Lycée Simone Weil",
                    "diplomes" : [
                        {"libelle" : "BTS Informatique de gestion"},
                        {"libelle" : "Baccalauréat série Scientifique"}
                    ]
                }
            ]
        },
        {
            "id" : "devLanguage",
            "titre" : "Langages",
            "items" : [
                {"libelle" : "PHP"},
                {"libelle" : "SQL"},
                {"libelle" : "Javascript"},
                {"libelle" : "HTML"},
                {"libelle" : "CSS"}
            ]
        },
        {
            "id" : "devTools",
            "titre" : "Outils",
            "items" : [
                {"libelle" : "VS Code"},
                {"libelle" : "SASS"},
                {"libelle" : "GitHub"},
                {"libelle" : "Figma"},
                {"libelle" : "Notion"}
            ]
        }
    ],
    "carriere" : [
        {
            "id": "1",
            "metier": "Manager de Projets Digital",
            "employeur": "LOCAM SAS",
            "lieu": "Saint-Etienne, LOIRE",
            "dates": "1 an (2022/2023)",
            "description": "Gestion du projet de refonte de l’extranet partenaires dans le contexte du projet de transformation : Gestion du planning et du budget, Conception et spécifications, Suivi des développements, Phase de tests,Déploiement d’API et de la signature électronique auprès des partenaires.",
            "link": "https://www.locam.fr"
        },
        {
            "id": "2",
            "metier": "Chargé de Missions Digital",
            "employeur": "LOCAM SAS",
            "lieu": "Saint-Etienne, LOIRE",
            "dates": "6 ans (2016/2022)",
            "description": "Gestion du projet de refonte de l’extranet partenaires dans le contexte du projet de transformation : Gestion du planning et du budget, Conception et spécifications, Suivi des développements, Phase de tests,Déploiement d’API et de la signature électronique auprès des partenaires.",
            "link": "https://www.locam.fr"
        },
        {
            "id": "3",
            "metier": "Webmarketer",
            "employeur": "LOCAM SAS",
            "lieu": "Saint-Etienne, LOIRE",
            "dates": "2 ans (2014/2016)",
            "description": "Gestion du projet de refonte de l’extranet partenaires dans le contexte du projet de transformation : Gestion du planning et du budget, Conception et spécifications, Suivi des développements, Phase de tests,Déploiement d’API et de la signature électronique auprès des partenaires.",
            "link": "https://www.locam.fr"
        },
        {
            "id": "4",
            "metier": "Analyste Informatique",
            "employeur": "LOCAM SAS",
            "lieu": "Saint-Etienne, LOIRE",
            "dates": "5 ans (2009/2014)",
            "description": "Gestion du projet de refonte de l’extranet partenaires dans le contexte du projet de transformation : Gestion du planning et du budget, Conception et spécifications, Suivi des développements, Phase de tests,Déploiement d’API et de la signature électronique auprès des partenaires.",
            "link": "https://www.locam.fr"
        }
    ],
    "projets": [
        {
            "id": "1",
            "libelle": "Moovizy",
            "color": "black",
            "competence": "UX Design / Figma",
            "background": "projet-moovizy-ux.png"
        },
        {
            "id": "2",
            "libelle": "",
            "color": "",
            "competence": "",
            "background": ""
        },
        {
            "id": "3",
            "libelle": "",
            "color": "",
            "competence": "",
            "background": ""
        },
        {
            "id": "4",
            "libelle": "",
            "competence": "",
            "background": ""
        },
        {
            "id": "5",
            "libelle": "",
            "competence": "",
            "background": ""
        },
        {
            "id": "6",
            "libelle": "",
            "competence": "",
            "background": ""
        },
        {
            "id": "7",
            "libelle": "",
            "competence": "",
            "background": ""
        },
        {
            "id": "8",
            "libelle": "",
            "competence": "",
            "background": ""
        }
    ]
}